slider/__init__.py
slider/__main__.py
slider/abc.py
slider/beatmap.py
slider/bit_enum.py
slider/cli.py
slider/client.py
slider/collection.py
slider/curve.py
slider/game_mode.py
slider/library.py
slider/mod.py
slider/position.py
slider/replay.py
slider/utils.py
slider/example_data/__init__.py
slider/example_data/beatmaps/__init__.py
slider/example_data/collections/__init__.py
slider/tests/__init__.py
slider/tests/test_beatmap.py
slider/tests/test_collection.py
slider/tests/test_utils.py
slider-0.8.4.dist-info/licenses/LICENSE
slider-0.8.4.dist-info/METADATA
slider-0.8.4.dist-info/WHEEL
slider-0.8.4.dist-info/top_level.txt
slider-0.8.4.dist-info/RECORD
