Metadata-Version: 2.4
Name: slider
Version: 0.8.4
Summary: Utilities for working with osu! files and data
Home-page: https://github.com/llllllllll/slider
Author: Joe Jevnik
Author-email: joejev@gmail.com
License: LGPLv3+
Classifier: Development Status :: 3 - Alpha
Classifier: License :: OSI Approved :: GNU Lesser General Public License v3 or later (LGPLv3+)
Classifier: Natural Language :: English
Classifier: Programming Language :: Python :: 3.6
Classifier: Programming Language :: Python :: 3 :: Only
Classifier: Topic :: Games/Entertainment
License-File: LICENSE
Requires-Dist: numpy
Requires-Dist: requests
Requires-Dist: scipy
Provides-Extra: dev
Requires-Dist: ruff; extra == "dev"
Requires-Dist: shed; extra == "dev"
Requires-Dist: pytest; extra == "dev"
Provides-Extra: cli
Requires-Dist: click; extra == "cli"
Dynamic: author
Dynamic: author-email
Dynamic: classifier
Dynamic: home-page
Dynamic: license
Dynamic: license-file
Dynamic: provides-extra
Dynamic: requires-dist
Dynamic: summary
